LICENSE
MANIFEST.in
README.md
pyproject.toml
requirements.txt
setup.py
moleculekit/__init__.py
moleculekit/align.py
moleculekit/bondguesser.py
moleculekit/cmlreader.py
moleculekit/config.py
moleculekit/dihedral.py
moleculekit/home.py
moleculekit/logging.ini
moleculekit/molecule.py
moleculekit/periodictable.py
moleculekit/pymolgraphics.py
moleculekit/pymolviewer.py
moleculekit/rcsb.py
moleculekit/rcsbsearch.py
moleculekit/rdkitintegration.py
moleculekit/readers.py
moleculekit/support.py
moleculekit/util.py
moleculekit/version.py
moleculekit/vmdgraphics.py
moleculekit/vmdviewer.py
moleculekit/writers.py
moleculekit/atomselect/__init__.py
moleculekit/atomselect/analyze.py
moleculekit/atomselect/atomselect.py
moleculekit/atomselect/languageparser.py
moleculekit/atomselect_utils/atomselect_utils.cpp
moleculekit/atomselect_utils/atomselect_utils.pyx
moleculekit/bondguesser_utils/bondguesser_utils.cpp
moleculekit/bondguesser_utils/bondguesser_utils.pyx
moleculekit/interactions/__init__.py
moleculekit/interactions/interactions.py
moleculekit/interactions/cationpi/cationpi.cpp
moleculekit/interactions/cationpi/cationpi.pyx
moleculekit/interactions/hbonds/hbonds.cpp
moleculekit/interactions/hbonds/hbonds.pyx
moleculekit/interactions/pipi/pipi.cpp
moleculekit/interactions/pipi/pipi.pyx
moleculekit/interactions/sigmahole/sigmahole.cpp
moleculekit/interactions/sigmahole/sigmahole.pyx
moleculekit/pdbx/__init__.py
moleculekit/pdbx/reader/PdbxContainers.py
moleculekit/pdbx/reader/PdbxParser.py
moleculekit/pdbx/reader/PdbxReader.py
moleculekit/pdbx/reader/__init__.py
moleculekit/pdbx/writer/PdbxWriter.py
moleculekit/pdbx/writer/__init__.py
moleculekit/ply/__init__.py
moleculekit/ply/lex.py
moleculekit/ply/yacc.py
moleculekit/projections/__init__.py
moleculekit/projections/metriccoordinate.py
moleculekit/projections/metricdihedral.py
moleculekit/projections/metricdistance.py
moleculekit/projections/metricfluctuation.py
moleculekit/projections/metricgyration.py
molkitten.egg-info/PKG-INFO
molkitten.egg-info/SOURCES.txt
molkitten.egg-info/dependency_links.txt
molkitten.egg-info/not-zip-safe
molkitten.egg-info/requires.txt
molkitten.egg-info/top_level.txt