Metadata-Version: 2.1
Name: molkitten
Version: 0.0.7
Summary: A molecule reading/writing and manipulation package.
Home-page: https://github.com/acellera/moleculekit/
Author: Acellera
Author-email: info@acellera.com
Classifier: Programming Language :: Python :: 3
Classifier: Operating System :: POSIX :: Linux
License-File: LICENSE
